{
	"parent": "minecraft:recipes/root",
	"rewards": {
		"recipes": [
			"platy:purple_dye_from_chorus_fruit"
		]
	},
	"criteria": {
		"has_chorus_fruit": {
			"trigger": "inventory_changed",
			"conditions": {
				"items": [{
					"items": ["chorus_fruit"]
				}]
			}
		},
		"has_recipe": {
			"trigger": "recipe_unlocked",
			"conditions": {
				"recipe": "platy:purple_dye_from_chorus_fruit"
			}
		}
	},
	"requirements": [
		[
			"has_chorus_fruit",
			"has_recipe"
		]
	]
}